isingm/__init__.py
isingm/metropolis.py
isingm-1.1.2.dist-info/LICENSE
isingm-1.1.2.dist-info/METADATA
isingm-1.1.2.dist-info/WHEEL
isingm-1.1.2.dist-info/RECORD
