Metadata-Version: 2.3
Name: isingm
Version: 1.1.2
Summary: A pythonic Ising model simulation
License: GPL-3.0-or-later
Keywords: physics,ising,montecarlo,ising model,metropolis algorithm
Author: pacidus
Author-email: pacidus@gmail.com
Requires-Python: >=3.7
Classifier: License :: OSI Approved :: GNU General Public License v3 or later (GPLv3+)
Classifier: Programming Language :: Python :: 3
Classifier: Programming Language :: Python :: 3.7
Classifier: Programming Language :: Python :: 3.8
Classifier: Programming Language :: Python :: 3.9
Classifier: Programming Language :: Python :: 3.10
Classifier: Programming Language :: Python :: 3.11
Classifier: Programming Language :: Python :: 3.12
Classifier: Programming Language :: Python :: 3.13
Requires-Dist: matplotlib (>=3.2.1)
Requires-Dist: numpy (>=1.18.2)
Project-URL: Repository, https://github.com/Pacidus/isingm
